nts/__init__.py
nts/cli.py
nts_radio_cli-0.2.0.dist-info/METADATA
nts_radio_cli-0.2.0.dist-info/WHEEL
nts_radio_cli-0.2.0.dist-info/entry_points.txt
nts_radio_cli-0.2.0.dist-info/licenses/LICENSE
nts_radio_cli-0.2.0.dist-info/RECORD
