Metadata-Version: 2.4
Name: nts-radio-cli
Version: 0.2.0
Summary: CLI tool to check what's playing on NTS Radio
Project-URL: Source, https://github.com/tiktuk/nts-radio-cli
Project-URL: Issues, https://github.com/tiktuk/nts-radio-cli/issues
Author-email: Tuk Bredsdorff <tukodeb@gmail.com>
License-File: LICENSE
Classifier: Development Status :: 3 - Alpha
Classifier: Environment :: Console
Classifier: Intended Audience :: End Users/Desktop
Classifier: License :: OSI Approved :: MIT License
Classifier: Operating System :: OS Independent
Classifier: Programming Language :: Python :: 3
Classifier: Programming Language :: Python :: 3.8
Classifier: Programming Language :: Python :: 3.9
Classifier: Programming Language :: Python :: 3.10
Classifier: Programming Language :: Python :: 3.11
Classifier: Programming Language :: Python :: 3.12
Classifier: Topic :: Multimedia :: Sound/Audio
Classifier: Topic :: Utilities
Requires-Python: >=3.8
Requires-Dist: click>=8.1.7
Requires-Dist: pillow>=10.0.0
Requires-Dist: pytz>=2024.2
Requires-Dist: requests>=2.32.3
Requires-Dist: rich-pixels>=1.1.1
Requires-Dist: rich>=13.9.4
